roadmap.py
setup.py
roadmap.egg-info/PKG-INFO
roadmap.egg-info/SOURCES.txt
roadmap.egg-info/dependency_links.txt
roadmap.egg-info/top_level.txt