Metadata-Version: 1.0
Name: roadmap
Version: 0.1
Summary: Object routing framework powered by regular expressions
Home-page: https://github.com/lightcatcher/roadmap
Author: Eric Martin
Author-email: e.a.martin1337@gmail.com
License: BSD
Platform: any
